{
  "brief_structure": [
    {
      "block": "Блок 1. Контактна інформація",
      "description": "Щоб ми могли оперативно уточнювати деталі та не заважати вам у невідповідний час.",
      "questions": [
        {
          "id": "1.1",
          "question": "Ваше ім’я.",
          "explanation": "Як до вас звертатися.",
          "type": "TEXT"
        },
        {
          "id": "1.2",
          "question": "Номер телефону.",
          "explanation": "Бажано мобільний.",
          "type": "TEL"
        },
        {
          "id": "1.3",
          "question": "Email",
          "explanation": "Буде використаний для офіційного зв'язку. Обов'язковий, якщо обрано Email у способах зв'язку.",
          "type": "TEXT"
        },
        {
          "id": "1.4",
          "question": "Зручний спосіб зв’язку.",
          "explanation": "Оберіть один або кілька варіантів.",
          "options": [
            "Дзвінки",
            "Email",
            "Telegram",
            "Viber",
            "WhatsApp",
            "Інше"
          ],
          "type": "MULTISELECT"
        },
        {
          "id": "1.5",
          "question": "Години для зв’язку.",
          "explanation": "Коли вам зручно приймати повідомлення чи дзвінки.",
          "type": "TEXT"
        },
        {
          "id": "1.6",
          "question": "Чи є інші учасники проєкту?",
          "explanation": "Перелічіть усіх, хто впливає на рішення.",
          "type": "REPEATING (Ім'я, Роль, Контакт)"
        }
      ]
    },
    {
      "block": "Блок 2. Концепція проєкту",
      "questions": [
        {
          "id": "2.1",
          "question": "У чому головна ідея вашого продукту?",
          "explanation": "Сформулюйте одним-двома реченнями.",
          "type": "TEXTAREA"
        },
        {
          "id": "2.2",
          "question": "Яку проблему вирішує ваш продукт?",
          "explanation": "Що саме зараз не так у користувачів?",
          "type": "TEXTAREA"
        },
        {
          "id": "2.3",
          "question": "Чим ваш підхід відрізняється від того, як люди справляються зараз?",
          "explanation": "Ваша ключова відмінність від конкурентів.",
          "type": "TEXTAREA"
        },
        {
          "id": "2.4",
          "question": "Якби ви могли описати продукт одним словом чи фразою, що б це було?",
          "explanation": "Коротко і яскраво.",
          "type": "TEXT"
        },
        {
          "id": "2.5",
          "question": "Чи є у вас вже прототип або MVP? Якщо так, що він вміє?",
          "explanation": "Поточний стан розробки.",
          "type": "TEXTAREA"
        },
        {
          "id": "2.6",
          "question": "Що для вас є головним критерієм успіху цього продукту?",
          "type": "TEXTAREA"
        }
      ]
    },
    {
      "block": "Блок 3. Бізнес-цілі",
      "questions": [
        {
          "id": "3.1",
          "question": "Які ключові бізнес-цілі ви ставите перед продуктом?",
          "explanation": "Цілі на найближчий рік-три.",
          "type": "TEXTAREA"
        },
        {
          "id": "3.2",
          "question": "Чи планується монетизація? Якщо так, то яка модель?",
          "explanation": "Підписка, реклама, продажі тощо.",
          "type": "TEXTAREA"
        },
        {
          "id": "3.3",
          "question": "Чи потрібна інтеграція з платіжними системами?",
          "explanation": "Stripe, PayPal, Fondy, LiqPay тощо.",
          "type": "TEXTAREA"
        },
        {
          "id": "3.4",
          "question": "Які ризики можуть завадити бізнес-успіху, на вашу думку?",
          "type": "TEXTAREA"
        }
      ]
    },
    {
      "block": "Блок 4. Цільова аудиторія",
      "questions": [
        {
          "id": "4.1",
          "question": "Опишіть портрет вашого ідеального користувача.",
          "type": "TEXTAREA"
        },
        {
          "id": "4.2",
          "question": "Які сегменти аудиторії ви хотіли б охопити в першу чергу?",
          "type": "TEXTAREA"
        },
        {
          "id": "4.3",
          "question": "Чи є користувач технічно підготовленим?",
          "options": ["Так", "Ні", "Частково"],
          "type": "SELECT"
        },
        {
          "id": "4.4",
          "question": "Як користувачі дізнаються про ваш продукт? Чи є канали залучення?",
          "explanation": "Реклама, SEO, соцмережі тощо.",
          "type": "TEXTAREA"
        }
      ]
    },
    {
      "block": "Блок 5. Конкурентне середовище",
      "questions": [
        {
          "id": "5.1",
          "question": "Кого ви вважаєте своїми основними конкурентами?",
          "explanation": "Включаючи непрямих (Excel, Notion).",
          "type": "TEXTAREA"
        },
        {
          "id": "5.2",
          "question": "Що вони роблять добре, а в чому програють?",
          "type": "TEXTAREA"
        },
        {
          "id": "5.3",
          "question": "Яка ваша ключова конкурентнта перевага?",
          "type": "TEXTAREA"
        }
      ]
    },
    {
      "block": "Блок 6. Архітектура даних",
      "questions": [
        {
          "id": "6.1",
          "question": "Чим саме ви будете керувати у системі?",
          "explanation": "Наприклад: Клієнти, Проєкти, Замовлення, Товари.",
          "type": "TEXTAREA"
        },
        {
          "id": "6.2",
          "question": "Чи пов’язані ці елементи між собою? Якщо так, то як саме?",
          "explanation": "Ієрархія та зв'язки.",
          "type": "TEXTAREA"
        },
        {
          "id": "6.3",
          "question": "Чи планується робота з великими обсягами даних?",
          "options": ["Так", "Ні", "Не впевнений"],
          "type": "SELECT"
        },
        {
          "id": "6.4",
          "question": "Чи потрібна історія змін або версійність даних?",
          "explanation": "Бачити, хто і коли змінив інформацію.",
          "type": "TEXTAREA"
        }
      ]
    },
    {
      "block": "Блок 7. Функціональні вимоги",
      "questions": [
        {
          "id": "7.1",
          "question": "Які функції критично потрібні для запуску?",
          "explanation": "Пріоритети для першої версії.",
          "type": "TEXTAREA"
        },
        {
          "id": "7.2",
          "question": "Чи потрібна робота з файлами (завантаження, зберігання, перегляд)?",
          "type": "TEXTAREA"
        },
        {
          "id": "7.3",
          "question": "Чи потрібен експорт та імпорт даних?",
          "type": "TEXTAREA"
        },
        {
          "id": "7.4",
          "question": "Наскільки складною має бути робота з даними (сортування, пошук, фільтрація)?",
          "explanation": "Опишіть рівень складності: простий пошук, фільтри за параметрами чи розширена фільтрація (як у Excel / Notion).",
          "type": "TEXTAREA"
        }
      ]
    },
    {
      "block": "Блок 8. Користувацькі сценарії",
      "questions": [
        {
          "id": "8.1",
          "question": "Чи матимуть користувачі у системі різні ролі? Якщо так, то уточніть які саме.",
          "explanation": "Адмін, Менеджер, Клієнт тощо.",
          "type": "TEXTAREA"
        },
        {
          "id": "8.2",
          "question": "Опишіть 3–5 головних сценаріїв використання продукту.",
          "explanation": "Що робить користувач у системі.",
          "type": "TEXTAREA"
        },
        {
          "id": "8.3",
          "question": "Який сценарій є найбільш критичним для успіху?",
          "type": "TEXTAREA"
        },
        {
          "id": "8.4",
          "question": "Чи потрібен гостьовий доступ або публічні сторінки?",
          "type": "TEXTAREA"
        },
        {
          "id": "8.5",
          "question": "Як має відбуватися знайомство нового користувача з продуктом?",
          "explanation": "Онбординг.",
          "options": [
            "Підказки",
            "Демо-дані",
            "Відео",
            "Поєднання підходів",
            "Інше"
          ],
          "type": "MULTISELECT + TEXT"
        }
      ]
    },
    {
      "block": "Блок 9. Візуальний вигляд.",
      "questions": [
        {
          "id": "9.1",
          "question": "Чи є у вас впізнаваний бренд (логотип, кольори шрифти)?",
          "type": "TEXTAREA + FILE"
        },
        {
          "id": "9.2",
          "question": "Чи є референси (приклади інтерфейсів), які вам подобаються?",
          "type": "TEXTAREA"
        },
        {
          "id": "9.3",
          "question": "Яке загальне враження має створювати дизайн?",
          "explanation": "Стиль, настрій.",
          "type": "TEXTAREA"
        },
        {
          "id": "9.4",
          "question": "Чи потрібна адаптація під мобільні пристрої?",
          "options": [
            "Так",
            "Ні"
          ],
          "type": "SELECT"
        },
        {
          "id": "9.5",
          "question": "Чи важливо, щоб продукту був зручний для всіх користувач, включно з людьми з обмеженими можливостями?",
          "type": "TEXTAREA"
        },
        {
          "id": "9.6",
          "question": "Чи має інтерфейс бути насиченим переходами та анімаціями?",
          "type": "TEXTAREA"
        }
      ]
    },
    {
      "block": "Блок 10. Контентне наповнення",
      "questions": [
        {
          "id": "10.1",
          "question": "Хто готуватиме тексти для інтерфейсу (лейбли, підказки, повідомлення)?",
          "type": "TEXTAREA"
        },
        {
          "id": "10.2",
          "question": "Чи потрібна багатомовність? Якщо так, які мови?",
          "type": "TEXTAREA"
        },
        {
          "id": "10.3",
          "question": "Чи будуть в системі зразки даних або демо-контент для нових користувачів?",
          "type": "TEXTAREA"
        }
      ]
    },
    {
      "block": "Блок 11. Інтеграції",
      "questions": [
        {
          "id": "11.1",
          "question": "З якими сервісами потрібна інтеграція?",
          "explanation": "Slack, CRM, Google Workspace тощо.",
          "type": "TEXTAREA"
        },
        {
          "id": "11.2",
          "question": "Чи має продукт бути відкритим для сторонніх розробників (API)?",
          "options": ["Так", "Ні"],
          "type": "SELECT"
        },
        {
          "id": "11.3",
          "question": "Як система має комунікувати з користувачем?",
          "explanation": "Email, Push, SMS, Telegram.",
          "type": "TEXTAREA"
        }
      ]
    },
    {
      "block": "Блок 12. Безпека та конфіденційність",
      "questions": [
        {
          "id": "12.1",
          "question": "Які дані є найбільш чутливими?",
          "type": "TEXTAREA"
        },
        {
          "id": "12.2",
          "question": "Чи є особливі вимоги до безпеки або законодавства?",
          "explanation": "GDPR, ISO тощо.",
          "type": "TEXTAREA"
        }
      ]
    },
    {
      "block": "Блок 13. Умови реалізації",
      "description": "Фінальні умови розробки та подальша підтримка.",
      "questions": [
        {
          "id": "13.1",
          "question": "Чи є у вас готові специфікації (ТЗ, макети, діаграми)?",
          "type": "TEXTAREA"
        },
        {
          "id": "13.2",
          "question": "Чи є особливі вимоги до хостингу (де буде розміщено продукт)?",
          "explanation": "Розміщення сервера, хмарні сервіси.",
          "options": [
            "Немає вимог",
            "Власний сервер",
            "Хмарна платформа",
            "Інше"
          ],
          "type": "SELECT + TEXTAREA"
        },
        {
          "id": "13.3",
          "question": "Які терміни ви вважаєте реалістичними для MVP?",
          "type": "TEXTAREA"
        },
        {
          "id": "13.4",
          "question": "Який бюджет ви орієнтовно закладаєте?",
          "type": "TEXTAREA"
        },
        {
          "id": "13.5",
          "question": "Чи буде технічна підтримка користувачів після запуску?",
          "type": "TEXTAREA"
        },
        {
          "id": "13.6",
          "question": "Як ви бачите процес збору зворотного відгуку?",
          "type": "TEXTAREA"
        }
      ]
    }
  ]
}
